<?xml version="1.0" encoding="UTF-8"?><record_update>
    <sys_choice action="DELETE" field="u_what_needed" table="x_58872_needit_needit" version="3">
        <sys_choice_set action="DELETE">
            <element>u_what_needed</element>
            <name>x_58872_needit_needit</name>
            <sys_class_name/>
            <sys_created_by/>
            <sys_created_on/>
            <sys_id/>
            <sys_mod_count/>
            <sys_name/>
            <sys_package/>
            <sys_policy/>
            <sys_scope/>
            <sys_update_name/>
            <sys_updated_by/>
            <sys_updated_on>2020-02-05 18:00:05</sys_updated_on>
        </sys_choice_set>
    </sys_choice>
    <sys_update_version action="INSERT_OR_UPDATE">
        <action>DELETE</action>
        <application/>
        <file_path/>
        <instance_id>a23d7734dba8ff003050ac44d496199d</instance_id>
        <instance_name>dev77941</instance_name>
        <name>sys_choice_x_58872_needit_needit_u_what_needed</name>
        <payload><![CDATA[<?xml version="1.0" encoding="UTF-8"?><record_update><sys_choice action="DELETE" field="u_what_needed" table="x_58872_needit_needit" version="3"><sys_choice_set action="DELETE"><element>u_what_needed</element><name>x_58872_needit_needit</name><sys_class_name/><sys_created_by/><sys_created_on/><sys_id/><sys_mod_count/><sys_name/><sys_package/><sys_policy/><sys_scope/><sys_update_name/><sys_updated_by/><sys_updated_on>2020-02-05 18:00:05</sys_updated_on></sys_choice_set></sys_choice></record_update>]]></payload>
        <payload_hash>-429457270</payload_hash>
        <record_name>Task.u_what_needed</record_name>
        <reverted_from/>
        <source>4a2a156307260010549efa7f7c1ed0b3</source>
        <source_table>sys_update_set</source_table>
        <state>previous</state>
        <sys_created_by>admin</sys_created_by>
        <sys_created_on>2020-02-05 18:00:05</sys_created_on>
        <sys_id>7aa8eb1907f24010549efa7f7c1ed0c4</sys_id>
        <sys_mod_count>0</sys_mod_count>
        <sys_recorded_at>170168255fb0000001</sys_recorded_at>
        <sys_updated_by>admin</sys_updated_by>
        <sys_updated_on>2020-02-05 18:00:05</sys_updated_on>
        <type>Choice list</type>
        <update_guid>f2a8eb19b5f24010ee234563615efec4</update_guid>
        <update_guid_history>f2a8eb19b5f24010ee234563615efec4:-429457270,fea8eb1929f24010ceef399b060e2bc0:1264701252,bea8eb19e0f24010243eb81e574411bd:-1001554480,7ea8eb1981f24010270684627dc24aba:1291032590,3ea8eb1950f240100d7265a7e0f3c2b7:1977964177,faa8eb19baf2401014810f9437d490b4:-1752887133,baa8eb19aff24010fbfe9884397d0cb1:103642638,7aa8eb19e6f2401009fb3dd066f799ae:2515242,65f5f2cd08b2001073a075c7d0a15e57:-1460202391</update_guid_history>
    </sys_update_version>
    <sys_metadata_delete action="INSERT_OR_UPDATE">
        <sys_audit_delete/>
        <sys_class_name>sys_metadata_delete</sys_class_name>
        <sys_created_by>admin</sys_created_by>
        <sys_created_on>2020-02-05 18:00:15</sys_created_on>
        <sys_db_object display_value="" name="sys_choice_set">sys_choice_set</sys_db_object>
        <sys_id>78b86f1907f24010549efa7f7c1ed08b</sys_id>
        <sys_metadata>78b86f1907f24010549efa7f7c1ed08b</sys_metadata>
        <sys_mod_count>0</sys_mod_count>
        <sys_name>u_what_needed</sys_name>
        <sys_package display_value="NeedIt" source="x_58872_needit">6ead8e780f603200cd674f8ce1050ed1</sys_package>
        <sys_parent/>
        <sys_policy/>
        <sys_scope display_value="NeedIt">6ead8e780f603200cd674f8ce1050ed1</sys_scope>
        <sys_scope_delete display_value="">94872a8897db403e8ee69a431de2fca4</sys_scope_delete>
        <sys_update_name>sys_choice_x_58872_needit_needit_u_what_needed</sys_update_name>
        <sys_update_version display_value="sys_choice_x_58872_needit_needit_u_what_needed">7aa8eb1907f24010549efa7f7c1ed0c4</sys_update_version>
        <sys_updated_by>admin</sys_updated_by>
        <sys_updated_on>2020-02-05 18:00:15</sys_updated_on>
    </sys_metadata_delete>
</record_update>
